TLV.py
TLV493D-1.0.1.dist-info/METADATA
TLV493D-1.0.1.dist-info/WHEEL
TLV493D-1.0.1.dist-info/top_level.txt
TLV493D-1.0.1.dist-info/RECORD
