Metadata-Version: 2.1
Name: TLV493D
Version: 1.0.1
Summary: CircuitPython driver for 3D Magnetic Sensor.
Home-page: https://github.com/Infineon/RaspberryPi_TLV
License: MIT
Platform: UNKNOWN
Classifier: Development Status :: 3 - Alpha
Classifier: Intended Audience :: Developers
Classifier: Topic :: Software Development :: Libraries
Classifier: Topic :: System :: Hardware
Classifier: License :: OSI Approved :: MIT License
Classifier: Programming Language :: Python :: 3
Classifier: Programming Language :: Python :: 3.4
Classifier: Programming Language :: Python :: 3.5
